ltbfiles/__init__.py
ltbfiles/autoimagelog.py
ltbfiles/ltbfiles.py
ltbfiles-4.3.0.dist-info/licenses/LICENSE_GPL_v3.txt
ltbfiles-4.3.0.dist-info/METADATA
ltbfiles-4.3.0.dist-info/WHEEL
ltbfiles-4.3.0.dist-info/top_level.txt
ltbfiles-4.3.0.dist-info/RECORD
