Metadata-Version: 2.4
Name: ltbfiles
Version: 4.3.0
Summary: Module for loading of files created with spectrometers from LTB
Author: Sven Merk
Project-URL: Homepage, https://gitlab.com/ltb_berlin/ltb_files
Project-URL: Bug Tracker, https://gitlab.com/ltb_berlin/ltb_files/-/issues
Project-URL: Docs, https://ltb_berlin.gitlab.io/ltb_files/ltbfiles.html
Classifier: Programming Language :: Python :: 3.8
Classifier: Programming Language :: Python :: 3.9
Classifier: Programming Language :: Python :: 3.10
Classifier: Programming Language :: Python :: 3.11
Classifier: Programming Language :: Python :: 3.12
Classifier: Programming Language :: Python :: 3.13
Classifier: Programming Language :: Python :: 3.14
Classifier: Operating System :: OS Independent
Requires-Python: >=3.8
License-File: LICENSE_GPL_v3.txt
Requires-Dist: numpy
Requires-Dist: pandas
Requires-Dist: pillow
Requires-Dist: python-dateutil
Provides-Extra: tests
Requires-Dist: pytest; extra == "tests"
Requires-Dist: pytest-cov; extra == "tests"
Dynamic: license-file
